r2lab/__init__.py
r2lab/argparse_additions.py
r2lab/hostnames.py.trash
r2lab/logging-debug.conf
r2lab/mapdataframe.py
r2lab/prepare.py
r2lab/r2labmap.py
r2lab/sidecar.py
r2lab/sidecar_payload.py
r2lab/utils.py
r2lab/version.py
r2lab/working-and-broken
r2lab/ws.py
r2lab/ws.py.bak
r2lab-0.11.0.dist-info/METADATA
r2lab-0.11.0.dist-info/WHEEL
r2lab-0.11.0.dist-info/RECORD
