Metadata-Version: 2.1
Name: r2lab
Version: 0.7.0
Summary: Basic utilities regarding the R2lab testbed
Home-page: http://r2lab.readthedocs.io
Author: Thierry Parmentelat
Author-email: thierry.parmentelat@inria.fr
License: CC BY-SA 4.0
Classifier: Development Status :: 4 - Beta
Classifier: Environment :: Console
Classifier: Intended Audience :: Information Technology
Classifier: Programming Language :: Python :: 3.5
Requires-Dist: websockets
Requires-Dist: asynciojobs
Requires-Dist: apssh
Provides-Extra: sidecar
Requires-Dist: websockets; extra == "sidecar"
Provides-Extra: prepare
Requires-Dist: apssh; extra == "prepare"
Provides-Extra: mapdataframe
Requires-Dist: pandas; extra == "mapdataframe"
Provides-Extra: all
Requires-Dist: websockets; extra == "all"
Requires-Dist: pandas; extra == "all"
Requires-Dist: apssh; extra == "all"
